odoo/addons/account_followup_subscribe/LICENSE
odoo/addons/account_followup_subscribe/README.rst
odoo/addons/account_followup_subscribe/__init__.py
odoo/addons/account_followup_subscribe/__manifest__.py
odoo/addons/account_followup_subscribe/images/screen.png
odoo/addons/account_followup_subscribe/models/__init__.py
odoo/addons/account_followup_subscribe/models/account_followup_report.py
odoo/addons/account_followup_subscribe/static/description/icon.png
odoo/addons/account_followup_subscribe/static/description/index.html
odoo/addons/account_followup_subscribe/tests/TEST_INSTRUCTIONS.rst
odoo/addons/account_followup_subscribe/wizard/followup_manual_reminder.py
odoo_addon_account_followup_subscribe-18.0.1.0.0.dist-info/METADATA
odoo_addon_account_followup_subscribe-18.0.1.0.0.dist-info/WHEEL
odoo_addon_account_followup_subscribe-18.0.1.0.0.dist-info/top_level.txt
odoo_addon_account_followup_subscribe-18.0.1.0.0.dist-info/RECORD
